{
  "contact": {
    "description": "Engineering Manager with 9 years of experience in leading teams & developing software projects from concept to implementation.",
    "ctas": [
      {
        "title": "Contact Me",
        "url": "mailto:madelinelise@gmail.com",
        "type": "primary"
      },
      {
        "title": "Download Resume",
        "url": "/madeline-jensen-resume.pdf",
        "type": "secondary"
      }
    ]
  },
  "jobs": [
    {
      "dates": "November 2021 - Present",
      "title": "Engineering Manager",
      "company": "O3 World",
      "descs": [
        {
          "title": "Directly manage the professional growth (and advocate) for engineers with a wide range of seniority."
        },
        {
          "title": "Partner with product, design, and project management teams to architect and oversee the development, release cycles, and team resourcing of enterprise software development projects."
        },
        {
          "title": "Be a key player in implementing a solid engineering practice. This largely involves empowering my team to be part of the solution process to determine what is best practice and what tools to evaluate for our projects."
        }
      ]
    },
    {
      "dates": "June 2019 - Nov 2019",
      "title": "Senior Developer",
      "company": "Mediacurrent",
      "descs": [
        {
          "title": "Lead developer for enterprise open-source projects using React, Gatsby & Drupal. Including performing discoveries for new builds, building out technical specifications, and leading the team through implementation."
        },
        {
          "title": "Facilitated learning and growth opportunities for the team by creating training, mentorship and internship programs."
        }
      ]
    },
    {
      "dates": "Dec 2016 - June 2019",
      "title": "Supervisor, Web Services",
      "company": "Volusia County Schools",
      "descs": [
        {
          "title": "Directly managed the growth of each member of the web services team and all web properties for the school district, including the redesign of 70 school websites and a district website."
        }
      ]
    },
    {
      "dates": "Dec 2014 - Dec 2016",
      "title": "Manager, Web Content",
      "company": "Furniture Leisure",
      "descs": [
        {
          "title": "Content manager and strategist for 5 eCommerce websites. Oversaw the relaunch of 2 eCommerce websites to an upgraded system, new design, and improved content for SEO."
        }
      ]
    },
    {
      "dates": "Jan 2014 - Jan 2018",
      "title": "Bachelor's in Science - Information Technology",
      "company": "Daytona State College"
    }
  ],
  "project_items": [
    {
      "title": "Be Well Work Well",
      "url": "https://www.pwc.com/us/en/about-us/purpose-and-values/well-being-learning-project.html"
    },
    {
      "title": "MagMutual",
      "url": "https://www.magmutual.com/"
    },
    {
      "title": "Scholar's Edge 529 ",
      "url": "https://scholarsedge529.com/"
    },
    {
      "title": "NASDAQ",
      "url": "https://www.nasdaq.com/"
    },
    {
      "title": "Harvard College",
      "url": "https://college.harvard.edu/"
    },
    {
      "title": "Shirely Ryan Ability Lab",
      "url": "https://www.sralab.org/"
    },
    {
      "title": "SEI Employee Platform",
      "url": "https://seic.com/"
    },
    {
      "title": "Penn State News",
      "url": "https://news.psu.edu/"
    },
    {
      "title": "Brand USA",
      "url": "https://www.visittheusa.com/"
    },
    {
      "title": "Vertex",
      "url": "https://www.vertexinc.com/"
    },
    {
      "title": "Rain Distribution",
      "url": "https://www.drupal.org/project/rain"
    },
    {
      "title": "Collective Directory Distribution",
      "url": "https://www.drupal.org/project/collective"
    },
    {
      "title": "@o3world/generator-drupal-theme",
      "url": "https://www.npmjs.com/package/@o3world/generator-drupal-theme"
    },
    {
      "title": "@o3world/generator-react-project",
      "url": "https://www.npmjs.com/package/@o3world/generator-react-project"
    }
  ],
  "logo_items": [
    {
      "title": "sei",
      "url": "https://seic.com/",
      "img": "/logos/sei.jpg"
    },
    {
      "title": "AIM",
      "url": "https://alzimpact.org/",
      "img": "/logos/aim.png"
    },
    {
      "title": "NASDAQ",
      "url": "https://www.nasdaq.com/",
      "img": "/logos/nasdaq.png"
    },
    {
      "title": "Harvard",
      "url": "https://college.harvard.edu/",
      "img": "/logos/harvard.png"
    },
    {
      "title": "PWC",
      "url": "https://www.pwc.com/us/en/the-new-equation.html",
      "img": "/logos/pwc.png"
    },
    {
      "title": "Principal",
      "url": "https://www.principal.com/",
      "img": "/logos/principal.png"
    }
  ],
  "mng_skill_items": [
    {
      "title": "Hiring + talent retention"
    },
    {
      "title": "Forecasting + resource planning"
    },
    {
      "title": "1:1s, performance reviews, PIPs"
    },
    {
      "title": "Cross dept. communication"
    },
    {
      "title": "Continual improvement"
    },
    {
      "title": "Scrum + Agile practices"
    },
    {
      "title": "Engineering practice development"
    },
    {
      "title": "Pre-sales / project estimations"
    }
  ],
  "tech_skill_items": [
    {
      "title": "React"
    },
    {
      "title": "Javascript"
    },
    {
      "title": "CSS + SCSS"
    },
    {
      "title": "GraphQL"
    },
    {
      "title": "Gatsby"
    },
    {
      "title": "Next.js"
    },
    {
      "title": "Git"
    },
    {
      "title": "CI / CD"
    },
    {
      "title": "Drupal 7/8/9"
    },
    {
      "title": "Storybook"
    },
    {
      "title": "Patternlab"
    },
    {
      "title": "Solutions architecture"
    },
    {
      "title": "Component based development"
    },
    {
      "title": "Headless + decoupled architecture"
    }
  ],
  "thought_items": [
    {
      "title": "YouTube: Theming with Components - Video Series",
      "url": "https://www.youtube.com/playlist?list=PLu-MxhbnjI9oEF9uR59Sq66_7Pf4guwG1"
    },
    {
      "title": "Webinar: When Drupal Met Gatsby, an Early Adopters Case Study",
      "url": "https://www.youtube.com/watch?v=t7kQzh6sBbE"
    },
    {
      "title": "Webinar: Real World Decoupled Drupal & Gatsby",
      "url": "https://www.mediacurrent.com/videos/webinar-decoupled-drupal-and-gatsby-real-world"
    },
    {
      "title": "Article: Meet the Team - Madeline Jensen",
      "url": "https://www.o3world.com/news/meet-the-team-madeline-jensen/"
    },
    {
      "title": "Event: STEM Goes Red - Mentorship Panel",
      "url": "https://events.bizzabo.com/351393/home"
    },
    {
      "title": "Article: Superior experiences with an “edge”",
      "url": "https://www.o3world.com/news/superior-experiences-with-an-edge/"
    }
  ]
}